{
  "CreateNewPasswordPage.titleCreateNewPassword": "Create New Password",
  "CreateNewPasswordPage.messageErrorPasswordSameAsBefore": "Password cannot be the same as before",
  "CreateNewPasswordPage.messageErrorPasswordRequired": "Password is required.",
  "CreateNewPasswordPage.messageErrorPasswordFormat": "Password must contain uppercase, lowercase letters and numbers. Minimum 8 characters.",
  "CreateNewPasswordPage.placeholderPassword": "Password",
  "CreateNewPasswordPage.messageErrorConfirmPasswordRequired": "Confirm Password is required.",
  "CreateNewPasswordPage.messageErrorPasswordNotMatch": "Passwords do not match.",
  "CreateNewPasswordPage.placeholderConfirmPassword": "Confirm Password",
  "CreateNewPasswordPage.buttonChangePassword": "Change Password",
  "CreateNewPasswordPage.altMuatransLogo": "Muatrans Logo",
  "CreateNewPasswordPage.ariaLabelTogglePasswordVisibility": "Toggle password visibility",
  "CreateNewPasswordPage.altToggleVisibility": "Toggle visibility",
  "CreateNewPasswordPage.ariaLabelToggleConfirmPasswordVisibility": "Toggle confirm password visibility",
  "LoginPage.errorEmailRequired": "WhatsApp Number / Email is required.",
  "LoginPage.errorEmailInvalid": "Invalid email format.",
  "LoginPage.errorPasswordRequired": "Password is required.",
  "LoginPage.errorEmailIncorrect": "The WhatsApp Number / Email you entered is incorrect",
  "LoginPage.errorPasswordIncorrect": "The password you entered is incorrect",
  "LoginPage.alertLoginSuccess": "Login Successful!",
  "LoginPage.altMuatransLogo": "Muatrans Logo",
  "LoginPage.titleWelcome": "Welcome to muatrans",
  "LoginPage.descriptionIntro": "Get cargo anytime, anywhere. Find instant cargo shipments that match your fleet in muatrans. Manage your journey more efficiently and maximize your income",
  "LoginPage.placeholderEmailOrPhone": "WhatsApp Number / Email",
  "LoginPage.placeholderPassword": "Password",
  "LoginPage.ariaLabelTogglePassword": "Toggle password visibility",
  "LoginPage.altToggleVisibility": "Toggle visibility",
  "LoginPage.labelStayLoggedIn": "Stay Logged In",
  "LoginPage.linkForgotPassword": "Forgot Password?",
  "LoginPage.buttonLogin": "Login",
  "VerifikasiDitolakPage.titleVerificationStopped": "Verification Process Successfully Stopped",
  "VerifikasiDitolakPage.descriptionNoMoreEmails": "You will no longer receive verification emails from",
  "SuccessPage.titleRegistrationSuccess": "Congratulations, Your Registration is Successful",
  "SuccessPage.descriptionAccountVerified": "Your Muatrans Transporter account has been successfully registered and verified",
  "SuccessPage.buttonLoginToMuatrans": "Log in to Muatrans",
  "SetPasswordPage.altDecorationTopLeft": "Top Left Decoration",
  "SetPasswordPage.altDecorationBottomRight": "Bottom Right Decoration",
  "SetPasswordPage.altLogoMuatMuat": "MuatMuat Logo",
  "SetPasswordPage.altEmailVerification": "Email Verification Successful",
  "SetPasswordPage.altToggleVisibility": "Toggle visibility",
  "SetPasswordPage.tagline": "Journey Made Easy Together",
  "SetPasswordPage.titleEmailVerificationSuccess": "Email Verification Successful",
  "SetPasswordPage.descriptionSetPassword": "Your email has been successfully registered, please create a password for your account below",
  "SetPasswordPage.placeholderPassword": "Password",
  "SetPasswordPage.placeholderConfirmPassword": "Confirm Password",
  "SetPasswordPage.errorPasswordRequired": "Password is required.",
  "SetPasswordPage.errorPasswordInvalid": "Password must contain uppercase, lowercase, and numbers. Minimum 8 characters",
  "SetPasswordPage.errorConfirmPasswordRequired": "Confirm Password is required.",
  "SetPasswordPage.errorPasswordMismatch": "Passwords do not match",
  "SetPasswordPage.alertPasswordSuccessful": "Password created successfully!",
  "SetPasswordPage.buttonContinue": "Continue",
  "OtpContainer.messageResendSuccess": "OTP resent successfully",
  "OtpContainer.messageOtpExpired": "The OTP you entered has expired",
  "OtpContainer.messageOtpIncorrect": "The OTP you entered is incorrect",
  "OtpContainer.textEmailPasswordCreated": "Email and password have been successfully created.",
  "OtpContainer.textCheckWhatsapp": "Please check the WhatsApp message on your device to continue registration",
  "OtpContainer.labelWhatsappNumber": "Your WhatsApp Number",
  "OtpContainer.buttonChange": "Change",
  "OtpContainer.buttonResendOtp": "Resend OTP",
  "OtpContainer.titleRegistrationSuccess": "Congratulations, Your Registration is Successful",
  "OtpContainer.textAccountVerified": "Your Muatrans Transporter account has been successfully registered and verified",
  "OtpContainer.buttonLoginToMuatrans": "Login to Muatrans",
  "OtpContainer.titleChangeWhatsapp": "Change WhatsApp Number",
  "OtpContainer.messageChangeWhatsappSuccess": "Successfully changed your WhatsApp number",
  "ExpiredPage.titleVerificationExpired": "Verification Process Cannot Be Completed Due to Expired Link",
  "ExpiredPage.descriptionContactAdmin": "Please contact",
  "ExpiredPage.descriptionGetNewLink": "to get a new verification link",
  "AlreadySucceededPage.titleAlreadyVerified": "You Have Already Been Successfully Verified",
  "AlreadySucceededPage.descriptionAccountReady": "Your Transporter account is ready to use. Please login to your account or contact Muatrans Customer Service if you have any issues",
  "AlreadySucceededPage.buttonLoginToMuatrans": "Login to Muatrans",
  "PasswordSuccessPage.titlePasswordChanged": "Password Successfully Changed",
  "PasswordSuccessPage.descriptionLoginWithNewPassword": "Please login to your Muatrans account using your new password",
  "PasswordSuccessPage.buttonLoginToMuatrans": "Login to Muatrans",
  "RingkasanStatusPesananScreen.titleRingkasanStatusPesanan": "Order Status Summary",
  "RingkasanStatusPesananScreen.badgeDriverBelumBerangkat": "{count} Driver Not Departed",
  "RingkasanStatusPesananScreen.textPesananAndaBeradaDalamTahap": "Your order is in the stage:",
  "ModalDetailStatusDriver.buttonDetailStatusDriver": "Driver Status Details",
  "ModalDetailStatusDriver.titleDetailStatusDriver": "Driver Status Details",
  "DetailPesananHeader.toastDokumenBerhasil": "Document successfully confirmed received",
  "DetailPesananHeader.toastErrorKonfirmasi": "An error occurred while confirming document",
  "DetailPesananHeader.menuUnduhBuktiPembayaran": "Download Payment Receipt",
  "DetailPesananHeader.menuUnduhDokumenDeliveryOrder": "Download Delivery Order Document",
  "DetailPesananHeader.titleDetailPesanan": "Order Details",
  "DetailPesananHeader.buttonDetailRefund": "Refund Details",
  "DetailPesananHeader.buttonUnduh": "Download",
  "DetailPesananHeader.buttonPesanUlang": "Reorder",
  "DetailPesananHeader.buttonDokumenDiterima": "Document Received",
  "DetailPesananHeader.buttonLihatUlasan": "View Review",
  "DetailPesananHeader.buttonBeriUlasan": "Give Review",
  "DetailPesananHeader.modalTitleInformasi": "Information",
  "DetailPesananHeader.modalDescriptionDokumenDiterima": "Click \"Done\", if you have received document proof to complete the order.",
  "DetailPesananHeader.modalButtonBelum": "Not Yet",
  "DetailPesananHeader.modalButtonSudahMenerima": "Already Received",
  "DetailPesananHeader.modalDescriptionPesanUlang": "Do you want to copy this order for reuse or create a new order with different details?",
  "DetailPesananHeader.modalButtonPesanBaru": "New Order",
  "DetailPesananHeader.modalButtonPesanUlang": "Reorder",
  "StatusPesananHeader.toastQRCodeBerhasilDisalin": "All Driver QR Code Link Successfully Copied",
  "StatusPesananHeader.labelKodePesanan": "Order Code",
  "StatusPesananHeader.labelStatusPesanan": "Order Status",
  "StatusPesananHeader.linkLihatBuktiPengiriman": "View Delivery Proof",
  "StatusPesananHeader.modalTitleBuktiPengiriman": "Document Delivery Proof",
  "StatusPesananHeader.labelTanggal": "Date",
  "StatusPesananHeader.labelFotoBuktiPengiriman": "Delivery Proof Photo",
  "StatusPesananHeader.altDokumen": "Document {index}",
  "StatusPesananHeader.labelCatatan": "Notes",
  "StatusPesananHeader.textCatatanContoh": "We inform you that the document has been sent and is now received by Mr. Ervin Sudjatmiko. Please confirm if there are any matters that need further follow-up. We are ready to help if clarification or additional completeness is needed. Thank you for your attention and cooperation.",
  "StatusPesananHeader.buttonMenuLainnya": "Other Menu",
  "StatusPesananHeader.menuLihatSemuaDriver": "View All Drivers",
  "StatusPesananHeader.menuBagikanQRCode": "Share All Driver QR Code",
  "StatusPesananHeader.modalTitleSemuaDriver": "All Drivers",
  "StatusPesananHeader.placeholderCariDriver": "Search Driver Name/License Plate",
  "StatusPesananHeader.buttonBagikanQRCode": "Share All Driver QR Code",
  "DriverRatingModal.labelRatingDriver": "Driver Rating",
  "DriverRatingModal.labelBerikanUlasan": "Give review for driver (Optional)",
  "DriverRatingModal.placeholderTulisUlasan": "Write your review about the driver",
  "DriverRatingModal.labelUlasanmu": "Your Review",
  "DriverRatingModal.buttonSimpan": "Save",
  "DriverRatingModal.toastErrorRatingWajib": "Driver rating is required",
  "DriverRatingModal.toastSuccessBerhasilMenyimpan": "Successfully saved review for driver",
  "DriverRatingModal.titleUlasan": "Review",
  "LacakArmadaScreen.titleLacakArmada": "Track Fleet",
  "LacakArmadaScreen.labelEstimasiTibaLokasi": "Estimated Arrival at<br/>{lokasi} Location",
  "LacakArmadaScreen.bottomSheetHeaderKeterangan": "Information",
  "LacakArmadaScreen.buttonDetailStatusDriver": "Driver Status Details",
  "Estimasi.labelMuat": "Estimated Loading Arrival {index}",
  "Estimasi.labelBongkar": "Estimated Unloading Arrival {index}",
  "RingkasanPembayaranPerubahanPesanan.headerDetailTambahanBiaya": "Additional Cost Details",
  "RingkasanPembayaranPerubahanPesanan.sectionBiayaPerubahanRute": "Route Change Cost",
  "RingkasanPembayaranPerubahanPesanan.labelSelisihJarakPerubahanLokasi": "Distance Difference for Location Change",
  "RingkasanPembayaranPerubahanPesanan.sectionBiayaAdministrasi": "Administrative Cost",
  "RingkasanPembayaranPerubahanPesanan.labelAdminUbahPesanan": "Order Change Admin",
  "RingkasanPembayaranPerubahanPesanan.sectionBiayaLainnya": "Other Costs",
  "RingkasanPembayaranPerubahanPesanan.labelAdminLayanan": "Service Admin",
  "RingkasanPembayaranPerubahanPesanan.labelPajak": "Tax",
  "RingkasanPembayaranPerubahanPesanan.labelTotalTambahanBiaya": "Total Additional<br/>Cost",
  "RingkasanPembayaranPerubahanPesanan.buttonBatalkanPerubahan": "Cancel Changes",
  "RingkasanPembayaranPerubahanPesanan.modalTitleBatalkanPerubahan": "Cancel Changes",
  "RingkasanPembayaranPerubahanPesanan.modalDescriptionKonfirmasiBatal": "Are you sure you want to cancel the changes?",
  "RingkasanPembayaranPerubahanPesanan.modalDescriptionKonsekuensiBatal": "If you cancel, you will not be able to make order changes again",
  "RingkasanPembayaranPerubahanPesanan.modalButtonBatalkanPerubahan": "Cancel Changes",
  "SewaArmadaFooter.labelTotalBiaya": "Total Cost",
  "SewaArmadaFooter.buttonLihatDetailBiaya": "View Cost Details",
  "SewaArmadaFooter.buttonLanjut": "Continue",
  "common.muatransLogo": "Muatrans Logo",
  "common.whatsappNumber": "WhatsApp Number",
  "ForgotPasswordPage.errorWhatsappRequired": "WhatsApp number is required.",
  "ForgotPasswordPage.errorWhatsappInvalid": "Invalid WhatsApp number format. Example: 081234567890",
  "ForgotPasswordPage.errorAccountNotFound": "Account not found. Try again with a different WhatsApp number",
  "ForgotPasswordPage.findYourAccount": "Find Your muatrans Account",
  "ForgotPasswordPage.enterWhatsappText": "Enter the WhatsApp number associated with your muatrans account",
  "ForgotPasswordPage.searchAccount": "Search Account",
  "BottomsheetCancellationHistory.labelCancelledBy": "Cancelled By",
  "BottomsheetCancellationHistory.labelCancellationDate": "Cancellation Date",
  "BottomsheetCancellationHistory.labelCancellationReason": "Cancellation Reason",
  "BottomsheetCancellationHistory.buttonViewCancellationReason": "View Cancellation Reason",
  "DetailRefundPesananResponsive.titleRefundDetail": "Refund Detail",
  "RefundStatusTimeline.labelRefundProcessing": "Refund is Being Processed",
  "RefundStatusTimeline.labelRefundCompleted": "Funds Sent",
  "RefundStatusTimeline.labelWIB": "WIB",
  "Legend.labelRefundProcessing": "Refund is Being Processed",
  "Legend.labelRefundCompleted": "Funds Sent",
  "Legend.titleRefundProcess": "Refund Process",
  "RekeningPengembalianDana.labelBankName": "Bank Name",
  "RekeningPengembalianDana.labelAccountNumber": "Account Number",
  "RekeningPengembalianDana.labelAccountHolderName": "Account Holder Name",
  "RekeningPengembalianDana.titleRefundAccount": "Refund Account",
  "DetailPengembalianDana.titleRefundDetails": "Refund Details",
  "DetailPengembalianDana.titleShippingServiceFee": "Shipping Service Fee",
  "DetailPengembalianDana.labelShippingServiceAmount": "Shipping Service Amount",
  "DetailPengembalianDana.titleWaitingTimeFee": "Waiting Time Fee",
  "DetailPengembalianDana.labelWaitingTimeAmount": "Waiting Time Amount (1 Driver)",
  "DetailPengembalianDana.titleAdminFee": "Administration Fee",
  "DetailPengembalianDana.labelCancellationAdmin": "Cancellation Admin",
  "DetailPengembalianDana.titleOtherFees": "Other Fees",
  "DetailPengembalianDana.labelRefundAdmin": "Refund Admin",
  "DetailPengembalianDana.labelTotalRefund": "Total Refund",
  "ModalBatalkanPesananResponsive.titleCancelOrder": "Cancel Order",
  "ModalBatalkanPesananResponsive.textAreYouSureCancelOrder": "Are you sure you want to cancel the order?",
  "ModalBatalkanPesananResponsive.textMakeSureRead": "Make sure you have read",
  "ModalBatalkanPesananResponsive.linkOurTerms": "Our Terms and Conditions.",
  "ModalBatalkanPesananResponsive.checkboxAgreeTerms": "Yes, I agree to the terms and conditions",
  "PendingUpdateFeePayment.altFleetFound": "Fleet found",
  "PendingUpdateFeePayment.messageOrderChangeSaved": "Order change information has been successfully saved.",
  "PendingUpdateFeePayment.messagePaymentReminder": "Please make payment within",
  "PendingUpdateFeePayment.messageAutoCancelWarning": "Changes will be automatically cancelled if the specified time limit is exceeded.",
  "ModalBatalkanPesananResponsive.textCancelWithPenalty": "Order cancellation will incur an admin fee of Rp100,000/unit.",
  "ModalBatalkanPesananResponsive.textIAgreeTo": "I agree to",
  "ModalBatalkanPesananResponsive.linkMuatransTerms": "Muatrans Terms and Conditions",
  "WaitingTimeBottomsheet.triggerViewDetails": "View Waiting Time Details",
  "WaitingTimeBottomsheet.titleDetails": "Waiting Time Details",
  "WaitingTimeBottomsheet.textFreeFirst12Hours": "FREE for the first 12 hours, waiting time fee applies after 12 hours",
  "WaitingTimeBottomsheet.labelDriver": "Driver :",
  "WaitingTimeBottomsheet.labelTotalDuration": "Total Duration:",
  "WaitingTimeBottomsheet.labelTotal": "Total",
  "WaitingSettlementModal.titleUnpaidBills": "Oops! There are still unpaid bills",
  "WaitingSettlementModal.textUnpaidBills": "There are unpaid bills. Please complete the payment to proceed.",
  "WaitingSettlementModal.buttonPayBill": "Pay Bill",
  "PreviewDriverScreen.breadcrumbManajemenDriver": "Driver Management",
  "PreviewDriverScreen.breadcrumbTambahDriverMassal": "Bulk Add Driver",
  "PreviewDriverScreen.breadcrumbDetailDriver": "Driver Details",
  "PreviewDriverScreen.messageSuccessAddDriver": "Successfully added {count} drivers.",
  "PreviewDriverScreen.messageErrorSaveDraft": "Failed to save driver draft. Please check the entered data.",
  "PreviewDriverScreen.messageSuccessSaveDraft": "Driver draft saved successfully.",
  "PreviewDriverScreen.titlePreviewDriver": "Preview Driver",
  "PreviewDriverScreen.buttonSaveAsDraft": "Save as Draft",
  "PreviewDriverScreen.buttonSave": "Save",
  "PreviewDriverScreen.titleConfirmDeleteDriver": "Are you sure you want to delete the driver?",
  "PreviewDriverScreen.buttonDelete": "Delete",
  "PreviewDriverScreen.buttonCancel": "Cancel",
  "PreviewDriverScreen.messageConfirmDeleteDriver": "Are you sure you want to delete the selected drivers? This action cannot be undone.",
  "PreviewDriverScreen.descriptionConfirmNavigation": "Are you sure you want to navigate away? The data you entered will not be saved",
  "PreviewDriverScreen.buttonYes": "Yes",
  "PreviewDriverScreen.messageConfirmNavigation": "The data you entered will not be saved. Are you sure you want to leave this page?",
  "TambahExcelScreen.headerTanggal": "Date",
  "TambahExcelScreen.headerDokumen": "Document",
  "TambahExcelScreen.headerNamaPengunggah": "Uploader Name",
  "TambahExcelScreen.headerStatus": "Status",
  "TambahExcelScreen.statusBerhasilMenambahDriver": "Successfully added driver",
  "TambahExcelScreen.statusGagalMenambahDriver": "Failed to add driver",
  "TambahExcelScreen.headerTindakan": "Action",
  "TambahExcelScreen.buttonUnduhReport": "Download Report",
  "TambahExcelScreen.messageSuccessAddDriver": "Successfully added {count} drivers",
  "TambahExcelScreen.messageErrorAddDriver": "Failed to add drivers. \n Check the report to see which drivers failed to be added",
  "TambahExcelScreen.messageSuccessDownloadTemplate": "Template downloaded successfully",
  "TambahExcelScreen.messageErrorTemplateNotAvailable": "Template not available",
  "TambahExcelScreen.messageErrorDownloadTemplate": "Failed to download template",
  "TambahExcelScreen.toggleSuksesUnggahFile": "Upload file success",
  "TambahExcelScreen.toggleGagalUnggahFile": "Upload file failed",
  "TambahExcelScreen.titleUnduhTemplateExcel": "Download Excel Template",
  "TambahExcelScreen.descriptionTemplateUsage": "Use this template to add multiple fleets at once.",
  "TambahExcelScreen.linkClickHere": "click here",
  "TambahExcelScreen.buttonUnduhTemplate": "Download Template",
  "TambahExcelScreen.titleUnggahFileExcel": "Upload Excel File",
  "TambahExcelScreen.descriptionUploadInstructions": "After completing driver information, upload file (.xls or .xlsx) max. 300 drivers in one file.",
  "TambahExcelScreen.placeholderDropzone": "Drag and drop files here or click to select files",
  "TambahExcelScreen.placeholderSearchDocument": "Search Document Name (min. 4 characters)",
  "TambahExcelScreen.titleRiwayatUnggahan": "Upload History Last 90 Days",
  "TambahExcelScreen.titleNoUploadHistory": "You don't have any upload history yet",
  "TambahMassalScreen.titleTambahDriverMassal": "Add Bulk Driver",
  "TambahMassalScreen.tabTambahDriverDenganExcel": "Add Driver with Excel",
  "TambahMassalScreen.tabTambahDriverMassal": "Add Bulk Driver",
  "TambahMassalScreen.tabDraft": "Draft",
  "TambahDriverMassalScreen.messageSuccessAddDriver": "Successfully added {count} drivers.",
  "TambahDriverMassalScreen.messageErrorSaveDriver": "Failed to save driver draft. Please check the entered data.",
  "TambahDriverMassalScreen.messageSuccessSaveDraft": "Driver draft saved successfully.",
  "TambahDriverMassalScreen.buttonSaveAsDraft": "Save as Draft",
  "TambahDriverMassalScreen.buttonSave": "Save",
  "TambahDriverMassalScreen.titleNotification": "Notification",
  "TambahDriverMassalScreen.messageCompleteDraftFirst": "Please complete the data in the Draft menu first.",
  "TambahDriverMassalScreen.messageUnfinishedDraft": "You have an unfinished add driver draft. Please save that data or delete the draft before adding new drivers",
  "TambahDriverMassalScreen.buttonCompleteDraft": "Complete Draft",
  "TambahDriverMassalScreen.titleConfirmDeleteDriver": "Are you sure you want to delete the driver?",
  "TambahDriverMassalScreen.buttonDelete": "Delete",
  "TambahDriverMassalScreen.buttonCancel": "Cancel",
  "TambahDriverMassalScreen.messageConfirmDeleteDriver": "Are you sure you want to delete the selected drivers? This action cannot be undone.",
  "Draft.messageSuccessAddDrivers": "Successfully added {count} Driver.",
  "Draft.messageErrorSaveDraft": "Failed to save driver draft. Please check the entered data.",
  "Draft.messageSuccessSaveDraft": "Driver draft successfully saved.",
  "Draft.messageErrorSaveFleet": "Failed to save fleet draft. Please check the entered data.",
  "Draft.titleNoDraftFleet": "No Fleet Draft Yet",
  "Draft.messageLoadingDrafts": "Loading drafts...",
  "Draft.titleFailLoadDraftFleet": "Failed to load fleet draft",
  "Draft.titleNoDraftFleetEmpty": "No Fleet Draft Yet",
  "Draft.buttonSaveAsDraft": "Save as Draft",
  "Draft.buttonSave": "Save",
  "Draft.titleConfirmDeleteDriver": "Are you sure you want to delete the driver?",
  "Draft.buttonDelete": "Delete",
  "Draft.buttonCancel": "Cancel",
  "Draft.messageConfirmDeleteFleet": "Are you sure you want to delete the selected fleet? This action cannot be undone.",
  "Draft.messageSuccessAddFleet": "Successfully added {count} fleet vehicles.",
  "Draft.messageErrorSaveFleetDraft": "Failed to save fleet draft. Please check the entered data.",
  "Draft.titleNoDraftFleetAvailable": "No Fleet Draft Available",
  "Draft.messageLoadingFleet": "Loading...",
  "Draft.titleErrorLoadFleet": "Failed to load fleet draft",
  "Draft.titleEmptyFleetDraft": "No Fleet Draft Yet",
  "Draft.buttonSaveAsDraftFleet": "Save as Draft",
  "Draft.buttonSaveFleet": "Save",
  "Draft.confirmDeleteTitle": "Are you sure you want to delete the fleet?",
  "Draft.confirmDeleteButton": "Delete",
  "Draft.cancelButton": "Cancel",
  "Draft.confirmDeleteMessage": "Are you sure you want to delete the selected fleet vehicles? This action cannot be undone.",
  "PopUpInformasi.slideTitle1": "Upload Driver in Bulk",
  "PopUpInformasi.slideContent1": "You can upload drivers in bulk using this feature.",
  "PopUpInformasi.slideTitle2": "Upload Driver in Bulk",
  "PopUpInformasi.slideContent2": "There are two options for uploading drivers in bulk: <ol><li>Using excel file</li><li>Filling in the available columns</li></ol>",
  "PopUpInformasi.slideTitle3": "Upload with Excel",
  "PopUpInformasi.slideContent3": "You can upload by following these steps: <ol><li>Download template</li><li>Fill in the available columns (you can see the procedure sheet example)</li><li>Upload the excel file in the available column</li></ol>",
  "PopUpInformasi.slideTitle4": "Fill Columns in Bulk",
  "PopUpInformasi.slideContent4": "You can upload by following these steps: <ol><li>Fill in the available columns</li><li>Click Save (if you want to add fleet click the Add button on that page)</li></ol>",
  "PopUpInformasi.messageSaving": "Saving...",
  "PopUpInformasi.labelDontShowAgain": "Don't show again",
  "DriverTable.messageErrorDuplicateWhatsapp": "WhatsApp number already registered",
  "DriverTable.placeholderSearchDriver": "Search Driver",
  "DriverTable.buttonAdd": "Add",
  "DriverTable.buttonDelete": "Delete",
  "DriverTable.labelTotalDrivers": "Total: {count} Driver",
  "DriverTable.labelFromTotal": "from {total}",
  "DriverTable.messageSearchResults": "Showing search results for &ldquo;{keyword}&rdquo;",
  "DriverTable.messageNoSearchResults": "No results for &ldquo;{keyword}&rdquo;",
  "DriverTable.headerDriver": "Driver*",
  "DriverTable.headerWhatsappNumber": "WhatsApp No.*",
  "DriverTable.headerKtpPhoto": "ID Card Photo*",
  "DriverTable.headerSimB2Photo": "B2 License Photo*",
  "DriverTable.headerSimB2Expiry": "B2 License Expiry*",
  "DriverTable.titleKeywordNotFound": "Keyword Not Found",
  "DriverTable.placeholderFullName": "Enter Full Name",
  "DriverTable.placeholderPhoneNumber": "Example: 08xxxxxxxxxx",
  "DriverTable.placeholderSelectDate": "Select Date",
  "DriverTable.altDriverPhoto": "Driver Photo",
  "PreviewArmada.breadcrumbManajemenArmada": "Fleet Management",
  "PreviewArmada.breadcrumbTambahArmadaMassal": "Bulk Add Fleet",
  "PreviewArmada.breadcrumbDetailArmada": "Fleet Details",
  "PreviewArmada.messageSuccessAddFleets": "Successfully added {count} fleet(s).",
  "PreviewArmada.messageErrorSaveDraft": "Failed to save fleet draft. Please check the entered data.",
  "PreviewArmada.messageSuccessSaveDraft": "Fleet draft saved successfully.",
  "PreviewArmada.messageErrorSaveDraftSecond": "Failed to save fleet draft. Please check the entered data.",
  "PreviewArmada.titlePreviewArmada": "Preview Fleet",
  "PreviewArmada.buttonSaveAsDraft": "Save as Draft",
  "PreviewArmada.buttonSave": "Save",
  "PreviewArmada.titleConfirmDeleteFleet": "Are you sure you want to delete the fleet?",
  "PreviewArmada.buttonDelete": "Delete",
  "PreviewArmada.buttonCancel": "Cancel",
  "PreviewArmada.messageConfirmDeleteFleet": "Are you sure you want to delete the selected fleet? This action cannot be undone.",
  "PreviewArmada.descriptionConfirmNavigation": "Are you sure you want to navigate away? The data you entered will not be saved",
  "PreviewArmada.buttonCancelNavigation": "Cancel",
  "PreviewArmada.buttonYes": "Yes",
  "PreviewArmada.messageConfirmNavigation": "The data you entered will not be saved. Are you sure you want to leave this page?",
  "TambahMassal.titleTambahArmadaMassal": "Bulk Add Fleet",
  "TambahMassal.tabTambahArmadaDenganExcel": "Add Fleet with Excel",
  "TambahMassal.tabTambahArmadaMassal": "Bulk Add Fleet",
  "TambahMassal.tabDraft": "Draft",
  "TambahExcel.headerTanggal": "Date",
  "TambahExcel.headerDokumen": "Document",
  "TambahExcel.headerNamaPengunggah": "Uploader Name",
  "TambahExcel.headerStatus": "Status",
  "TambahExcel.statusBerhasilMenambahArmada": "Successfully added fleet",
  "TambahExcel.statusGagalMenambahArmada": "Failed to add fleet",
  "TambahExcel.headerTindakan": "Action",
  "TambahExcel.buttonUnduhReport": "Download Report",
  "TambahExcel.toastBerhasilMenambahArmada": "Successfully added {totalRows} fleet",
  "TambahExcel.toastGagalMenambahArmada": "Failed to add fleet.\n Check the report to see which fleets failed to be added.",
  "TambahExcel.toastTemplateBerhasilDiunduh": "Template downloaded successfully",
  "TambahExcel.toastTemplateTidakTersedia": "Template not available",
  "TambahExcel.toastGagalMengunduhTemplate": "Failed to download template",
  "TambahExcel.toggleSuksesUnggahFile": "Successful file upload",
  "TambahExcel.toggleGagalUnggahFile": "Failed file upload",
  "TambahExcel.titleUnduhTemplateExcel": "Download Excel Template",
  "TambahExcel.descriptionGunakanTemplate": "Use this template to add multiple fleets at once.",
  "TambahExcel.linkKlikDisini": "click here",
  "TambahExcel.buttonMemuatTemplate": "Loading Template...",
  "TambahExcel.buttonUnduhTemplate": "Download Template",
  "TambahExcel.titleUnggahFileExcel": "Upload Excel File",
  "TambahExcel.descriptionSetelahMelengkapi": "After completing fleet information, upload file (.xls or .xlsx) max. 300 fleets in one file.",
  "TambahExcel.placeholderSeretDanLepas": "Drag and drop files here or click to select files",
  "TambahExcel.searchPlaceholderCariNamaDokumen": "Search Document Name (min. 4 characters)",
  "TambahExcel.titleRiwayatUnggahan90Hari": "Upload History Last 90 Days",
  "TambahExcel.dataNotFoundTitle": "You don't have any upload history yet",
  "TambahArmadaMassal.toastBerhasilMenambahkanArmada": "Successfully added {count} fleet(s).",
  "TambahArmadaMassal.toastGagalMenyimpanDraftArmada": "Failed to save fleet draft. Please check the entered data.",
  "TambahArmadaMassal.toastDraftArmadaBerhasilDisimpan": "Fleet draft saved successfully.",
  "TambahArmadaMassal.toastGagalMenyimpanDraftArmadaSecond": "Failed to save fleet draft. Please check the entered data.",
  "TambahArmadaMassal.buttonSimpanSebagaiDraft": "Save as Draft",
  "TambahArmadaMassal.buttonSimpan": "Save",
  "TambahArmadaMassal.titlePemberitahuan": "Notification",
  "TambahArmadaMassal.descriptionHarapSelesaikanData": "Please complete the data in the Draft menu first.",
  "TambahArmadaMassal.descriptionKamuMemilikiDraft": "You have an unfinished fleet addition draft. Please save the data or delete the draft before adding a new fleet",
  "TambahArmadaMassal.buttonSelesaikanDraft": "Complete Draft",
  "TambahArmadaMassal.titleConfirmDeleteArmada": "Are you sure you want to delete the fleet?",
  "TambahArmadaMassal.buttonHapus": "Delete",
  "TambahArmadaMassal.buttonBatal": "Cancel",
  "TambahArmadaMassal.messageConfirmDeleteArmada": "Are you sure you want to delete the selected fleet? This action cannot be undone.",
  "ArmadaTable.messageErrorLicensePlateDuplicate": "Vehicle license plate is already registered",
  "ArmadaTable.placeholderCariArmada": "Search Fleet",
  "ArmadaTable.buttonTambah": "Add",
  "ArmadaTable.buttonHapus": "Delete",
  "ArmadaTable.labelTotalArmada": "Total: {count} Fleet",
  "ArmadaTable.labelDariTotal": " of {total}",
  "ArmadaTable.messageSearchResults": "Showing search results for \"{keyword}\"",
  "ArmadaTable.messageNoSearchResults": "No results for \"{keyword}\"",
  "ArmadaTable.headerArmada": "Fleet*",
  "ArmadaTable.headerJenisTruk": "Truck Type*",
  "ArmadaTable.headerJenisCarrier": "Carrier Type*",
  "ArmadaTable.headerMerekKendaraan": "Vehicle Brand*",
  "ArmadaTable.headerTipeKendaraan": "Vehicle Type*",
  "ArmadaTable.headerTahunRegistrasi": "Vehicle Registration Year*",
  "ArmadaTable.headerDimensiCarrier": "Carrier Dimensions (Optional)",
  "ArmadaTable.headerNomorRangka": "Chassis Number*",
  "ArmadaTable.headerMasaBerlakuSTNK": "STNK Expiry Date*",
  "ArmadaTable.headerFotoSTNK": "STNK Photo*",
  "ArmadaTable.headerFotoPajakKendaraan": "Vehicle Tax Photo*",
  "ArmadaTable.headerKIRKendaraan": "Vehicle KIR*",
  "ArmadaTable.headerMasaBerlakuKIR": "KIR Expiry Date*",
  "ArmadaTable.headerFotoBukuKIR": "KIR Book Photo*",
  "ArmadaTable.headerEstimasiTanggalPemasanganGPS": "Estimated GPS Installation Date*",
  "ArmadaTable.titleKeywordNotFound": "Keyword Not Found",
  "ArmadaTable.altFotoArmadaDepan": "Front Fleet Photo",
  "ArmadaTable.placeholderPilihJenisTruk": "Select Truck Type",
  "ArmadaTable.placeholderPilihJenisCarrier": "Select Carrier Type",
  "ArmadaTable.placeholderPilihMerekKendaraan": "Select Vehicle Brand",
  "ArmadaTable.placeholderPilihTipeKendaraan": "Select Vehicle Type",
  "ArmadaTable.placeholderPilihTahun": "Select Year",
  "ArmadaTable.placeholderUnit": "Unit",
  "ArmadaTable.placeholderPilihTanggal": "Select Date",
  "ArmadaTable.sampaiDengan": "to",
  "PopUpInformasi.titleUnggahArmadaMassal": "Upload Fleet in Bulk",
  "PopUpInformasi.contentUnggahArmadaMassal": "You can upload fleets in bulk using this feature.",
  "PopUpInformasi.titleUnggahArmadaMassalSecond": "Upload Fleet in Bulk",
  "PopUpInformasi.contentDuaPilihanUnggah": "There are two options for uploading fleets in bulk: <ol><li>Using excel file</li><li>Filling in the available columns</li></ol>",
  "PopUpInformasi.titleUnggahDenganExcel": "Upload with Excel",
  "PopUpInformasi.contentUnggahDenganExcel": "You can upload with the following steps: <ol><li>Download template</li><li>Fill in the available columns (you can see the procedure sheet example)</li><li>Upload excel file in the available column</li></ol>",
  "PopUpInformasi.titleIsiKolomMassal": "Fill Columns in Bulk",
  "PopUpInformasi.contentIsiKolomMassal": "You can upload with the following steps: <ol><li>Fill in the available columns</li><li>Click Save (if you want to add fleet click the Add button on that page)</li></ol>",
  "PopUpInformasi.errorGagalMemperbarui": "Failed to update preferences",
  "PopUpInformasi.statusLoading": "Loading...",
  "PopUpInformasi.errorGagalMemuatPreferensi": "Failed to load popup preferences",
  "PopUpInformasi.errorTerjadiKesalahan": "An error occurred while loading data",
  "PopUpInformasi.statusMenyimpan": "Saving...",
  "PopUpInformasi.labelJanganTampilkanLagi": "Don't show again",
  "BottomSheetPreviousDriver.buttonViewPreviousDriver": "View Previous Driver",
  "BottomSheetPreviousDriver.titlePreviousDriver": "Previous Driver",
  "BottomSheetPreviousDriver.altDriverAvatar": "driver",
  "BottomSheetPreviousDriver.textDriverNotFound": "Driver not found",
  "BottomSheetPreviousDriver.buttonDriverStatusDetail": "Driver Status Details",
  "PendingUpdateFeePayment.toastFleetWillBeReprepared": "Fleet will be reprepared according to the changes made.",
  "UrgentIssueCard.statusNew": "new",
  "UrgentIssueCard.statusProcessing": "processing",
  "UrgentIssueCard.statusCompleted": "completed",
  "UrgentIssueCard.buttonProcess": "Process",
  "UrgentIssueCard.buttonCompleted": "Completed",
  "UrgentIssueCard.alertExceededTimeLimit": "Urgent Issue Report Exceeded Time Limit",
  "UrgentIssueCard.imageAltTransporterLogo": "Transporter Logo",
  "UrgentIssueCard.checkboxLabelGroupView": "Group View",
  "UrgentIssueCard.buttonContact": "Contact",
  "UrgentIssueCard.labelFleet": "Fleet",
  "UrgentIssueCard.descriptionMustArriveSoon": "must arrive at the loading location within 30 minutes. Please confirm with the driver to update the status.",
  "UrgentIssueCard.labelOrderNumber": "Order Number",
  "UrgentIssueCard.labelReportReceivedDate": "Report Received Date",
  "UrgentIssueCard.labelReportProcessedDate": "Report Processed Date",
  "UrgentIssueCard.buttonViewDetails": "View Details",
  "UrgentIssueCard.buttonHide": "Hide",
  "UrgentIssueCard.buttonChangeTransporter": "Change Transporter",
  "UrgentIssueCard.modalCompleteIssueDescription": "Are you sure you want to complete the urgent issue for order {orderCode}?",
  "UrgentIssueCard.modalButtonNo": "No",
  "UrgentIssueCard.modalButtonYes": "Yes",
  "UrgentIssueCard.modalProcessIssueDescription": "Are you sure you want to process the urgent issue for order {orderCode}?",
  "UrgentIssue.messageLoading": "Loading...",
  "UrgentIssue.messageNoReports": "There are no urgent issue reports",
  "UrgentIssue.messageNoReportsNew": "new",
  "UrgentIssue.messageNoReportsProcessing": "already processed",
  "UrgentIssue.messageNoReportsCompleted": "that have been completed",
  "UrgentIssue.filterStatus": "Status",
  "UrgentIssue.filterVehicleType": "Vehicle Type",
  "UrgentIssue.filterStatusScheduled": "Scheduled",
  "UrgentIssue.filterStatusWaiting": "Waiting for Loading Time",
  "UrgentIssue.filterStatusOnDuty": "On Duty",
  "UrgentIssue.filterStatusCompleted": "Delivery Completed",
  "UrgentIssue.filterStatusInactive": "Inactive",
  "UrgentIssue.filterVehicleTypeTruck": "Medium Truck 6x2 - Tank",
  "UrgentIssue.filterVehicleTypeColt": "Colt Diesel Double - Open Bed",
  "UrgentIssue.filterVehicleTypeDump": "Colt Diesel Double - Dump",
  "UrgentIssue.titleUrgentIssueReport": "Urgent Issue Report",
  "UrgentIssue.alertOverdueReports": "{count} Urgent Issue Reports Exceeded Deadline",
  "UrgentIssue.alertOverdueReportsAction": "Contact the relevant Transporter immediately to resolve the report.",
  "UrgentIssue.tabNew": "New",
  "UrgentIssue.tabProcessing": "Processing",
  "UrgentIssue.tabCompleted": "Completed",
  "UrgentIssueTransporter.messageLoading": "Loading...",
  "UrgentIssueTransporter.messageNoReports": "There are no urgent issue reports",
  "UrgentIssueTransporter.messageNoReportsNew": "new",
  "UrgentIssueTransporter.messageNoReportsProcessing": "already processed",
  "UrgentIssueTransporter.messageNoReportsCompleted": "that have been completed",
  "UrgentIssueTransporter.titleUrgentIssueReport": "Urgent Issue Report",
  "UrgentIssueTransporter.tabNew": "New",
  "UrgentIssueTransporter.tabProcessing": "Processing",
  "UrgentIssueTransporter.tabCompleted": "Completed",
  "UrgentIssueCardTransporter.buttonProcess": "Process",
  "UrgentIssueCardTransporter.statusCompleted": "Completed",
  "UrgentIssueCardTransporter.buttonViewDetail": "View Detail",
  "UrgentIssueCardTransporter.labelOrderNumber": "Order Number",
  "UrgentIssueCardTransporter.labelReportDate": "Report Date",
  "UrgentIssueCardTransporter.labelDateProcessed": "Report Processed Date",
  "UrgentIssueCardTransporter.buttonHide": "Hide",
  "UrgentIssueCardTransporter.noteProcessing": "Urgent issue is being handled",
  "UrgentIssueCardTransporter.noteCompleted": "Urgent issue is completed",
  "UrgentIssueCardTransporter.toastVehicleClick": "Testing click vehicle",
  "UrgentIssueCardTransporter.alertVehicleClick": "Testing click vehicle",
  "UrgentIssueCardTransporter.modalDescriptionComplete": "Are you sure you want to complete the urgent issue for order {orderCode}?",
  "UrgentIssueCardTransporter.buttonCancel": "No",
  "UrgentIssueCardTransporter.buttonConfirm": "Yes",
  "UrgentIssueCardTransporter.modalDescriptionProcess": "Are you sure you want to process the urgent issue for order {orderCode}?",
  "UrgentIssueCardTransporter.vehicleDescription": "Fleet {vehiclePlateNumber} {description}",
  "LaporanPendapatanPage.periodOptionAllPeriods": "All Periods (Default)",
  "LaporanPendapatanPage.periodOptionToday": "Today",
  "LaporanPendapatanPage.periodOptionLastWeek": "Last Week",
  "LaporanPendapatanPage.periodOptionLastMonth": "Last 30 Days",
  "LaporanPendapatanPage.periodOptionLastQuarter": "Last 90 Days",
  "LaporanPendapatanPage.periodOptionLastYear": "Last Year",
  "LaporanPendapatanPage.summaryCardTotalRevenue": "Total Revenue",
  "LaporanPendapatanPage.summaryCardUndisbursedFunds": "Total Undisbursed Funds",
  "LaporanPendapatanPage.summaryCardDisbursedFunds": "Total Disbursed Funds",
  "LaporanPendapatanPage.summaryCardThisMonthRevenue": "This Month's Revenue",
  "LaporanPendapatanPage.sourceAdditionalCost": "Additional Cost",
  "LaporanPendapatanPage.statusDisbursed": "Disbursed",
  "LaporanPendapatanPage.statusPartiallyDisbursed": "Partially Disbursed",
  "LaporanPendapatanPage.statusNotDisbursed": "Not Disbursed",
  "LaporanPendapatanPage.sourceRevenueAdjustment": "Revenue Adjustment",
  "LaporanPendapatanPage.sourceOrderRevenue": "Order Revenue",
  "LaporanPendapatanPage.tableColumnOrderNumber": "Order Number",
  "LaporanPendapatanPage.tableColumnSource": "Source",
  "LaporanPendapatanPage.tableColumnStatus": "Status",
  "LaporanPendapatanPage.tableColumnRevenueAmount": "Revenue Amount",
  "LaporanPendapatanPage.tableColumnUndisbursedFunds": "Undisbursed Funds",
  "LaporanPendapatanPage.tableColumnAction": "Action",
  "LaporanPendapatanPage.buttonDetail": "Detail",
  "LaporanPendapatanPage.filterCategoryStatus": "Status",
  "LaporanPendapatanPage.filterCategorySource": "Source",
  "LaporanPendapatanPage.titleLaporanPendapatan": "Revenue Report",
  "LaporanPendapatanPage.tooltipOrderRevenue": "Order Revenue:",
  "LaporanPendapatanPage.tooltipRevenueAdjustment": "Revenue Adjustment:",
  "LaporanPendapatanPage.tooltipAdditionalCost": "Additional Cost:",
  "LaporanPendapatanPage.emptyStateTitle": "No revenue report available",
  "LaporanPendapatanPage.emptyStateSubtitle": "Currently no revenue report is available. Let's start recording transactions so the report can appear!",
  "LaporanPendapatanPage.searchPlaceholder": "Search Orders",
  "DetailPendapatanPage.sourceRevenueAdjustment": "Revenue Adjustment",
  "DetailPendapatanPage.statusNotDisbursed": "Not Disbursed",
  "DetailPendapatanPage.tableColumnNumber": "No.",
  "DetailPendapatanPage.tableColumnDisbursementDate": "Disbursement Date",
  "DetailPendapatanPage.tableColumnDisbursedAmount": "Disbursed Amount",
  "DetailPendapatanPage.tableColumnRemainingAmount": "Remaining Undisbursed Funds",
  "DetailPendapatanPage.breadcrumbLaporanPendapatan": "Revenue Report",
  "DetailPendapatanPage.breadcrumbDetailPendapatan": "Revenue Details",
  "DetailPendapatanPage.titleDetailPendapatan": "Revenue Details",
  "DetailPendapatanPage.labelOrderCode": "Order Code",
  "DetailPendapatanPage.labelSource": "Source",
  "DetailPendapatanPage.labelStatus": "Status",
  "DetailPendapatanPage.titleIncomeDetails": "Income Details",
  "DetailPendapatanPage.labelInitialIncomeValue": "Initial Income Value",
  "DetailPendapatanPage.labelDetails": "Details",
  "LaporanPencairanDanaPage.periodOptionAllPeriods": "All Periods (Default)",
  "LaporanPencairanDanaPage.periodOptionToday": "Today",
  "LaporanPencairanDanaPage.periodOptionLastWeek": "Last Week",
  "LaporanPencairanDanaPage.periodOptionLastMonth": "Last 30 Days",
  "LaporanPencairanDanaPage.periodOptionLastQuarter": "Last 90 Days",
  "LaporanPencairanDanaPage.periodOptionLastYear": "Last Year",
  "LaporanPencairanDanaPage.tableColumnDate": "Date",
  "LaporanPencairanDanaPage.tableColumnDisbursementAmount": "Disbursement Amount",
  "LaporanPencairanDanaPage.tableColumnDisbursementAccount": "Disbursement Account",
  "LaporanPencairanDanaPage.tableColumnAction": "Action",
  "LaporanPencairanDanaPage.buttonDetail": "Detail",
  "LaporanPencairanDanaPage.filterCategoryDisbursementAccount": "Disbursement Account",
  "LaporanPencairanDanaPage.titleLaporanPencairan": "Disbursement Report",
  "LaporanPencairanDanaPage.infoTooltipDescription": "Monitor all fund disbursements you have received easily. This report records every transaction, complete with amount, date, and disbursement account.",
  "LaporanPencairanDanaPage.buttonDownload": "Download",
  "LaporanPencairanDanaPage.emptyStateTitle": "No disbursement report available",
  "LaporanPencairanDanaPage.emptyStateSubtitle": "Currently no disbursement report is available. After there are disbursement transactions, the report will appear here.",
  "DetailPencairanDanaPage.sourceOrderRevenue": "Order Revenue",
  "DetailPencairanDanaPage.sourceRevenueAdjustment": "Revenue Adjustment",
  "DetailPencairanDanaPage.tableColumnInvoiceNumber": "Invoice Number",
  "DetailPencairanDanaPage.tableColumnSource": "Source",
  "DetailPencairanDanaPage.tableColumnTotalIncome": "Total Income",
  "DetailPencairanDanaPage.breadcrumbLaporanPencairan": "Disbursement Report",
  "DetailPencairanDanaPage.breadcrumbRincianPencairan": "Disbursement Details",
  "DetailPencairanDanaPage.titleRincianPencairan": "Disbursement Details",
  "DetailPencairanDanaPage.buttonDownload": "Download",
  "DetailPencairanDanaPage.labelDisbursementDate": "Disbursement Date",
  "DetailPencairanDanaPage.labelDisbursementAccount": "Disbursement Account",
  "DetailPencairanDanaPage.emptyStateNoInvoiceData": "No Invoice Data Available",
  "DetailPencairanDanaPage.titleDisbursementSummary": "Disbursement Summary",
  "DetailPencairanDanaPage.labelGrossIncome": "Gross Income",
  "DetailPencairanDanaPage.labelIncomeAmount": "Income Amount",
  "DetailPencairanDanaPage.labelServiceAdmin": "Service Admin",
  "DetailPencairanDanaPage.labelOtherCosts": "Other Costs",
  "DetailPencairanDanaPage.labelDPP": "DPP",
  "DetailPencairanDanaPage.labelPPN": "VAT 12%",
  "DetailPencairanDanaPage.labelPPH": "Income Tax 2%",
  "DetailPencairanDanaPage.labelTotal": "Total",
  "ModalQRCodeDriver.toastQRCodeCopied": "QR Code link copied successfully",
  "ModalQRCodeDriver.titleQRCodeLocation": "QR Code Location",
  "ModalQRCodeDriver.instructionShowQRCode": "Show this QR Code to the driver to update their location",
  "ModalQRCodeDriver.buttonShareQRCode": "Share QR Code",
  "LeftPanel.breadcrumbDaftarPesanan": "Order List",
  "LeftPanel.breadcrumbDetailPesanan": "Order Details",
  "LeftPanel.breadcrumbLacakArmada": "Track Fleet",
  "LeftPanel.titleLacakArmada": "Track Fleet",
  "LeftPanel.titleDetailStatusDriver": "Driver Status Details",
  "AlertLabelEnum.messageRefundInProcess": "Refund is being processed.",
  "AlertLabelEnum.messageRefundCompleted": "Refund has been successfully processed.",
  "AlertLabelResponsiveEnum.messageReminderRepaymentOrderMobile": "<b>Your order has additional charges.</b><p>Please complete payment before <b>{date}.</b></p>",
  "AlertInfoEnum.messageShowQrcodeDriverInfo": "QR Code is required for the driver to proceed with loading or unloading goods.",
  "AlertInfoEnum.messageRefundInProcessInfo": "Refund is being processed, the amount will be adjusted after deducting <b>Cancellation Admin</b> and <b>Additional Charges</b>. For more information, contact Customer Service.",
  "AlertInfoEnum.messageRefundCompletedInfo": "The refund process has been successfully transferred to your account. For more information, contact Customer Service.",
  "getAlertMetadata.buttonLihatDetail": "View Details",
  "getAlertMetadata.buttonLihatPerubahan": "View Changes",
  "IncomeCards.titleDisbursed": "Disbursed",
  "IncomeCards.tooltipDisbursed": "Income that has been successfully disbursed to your account",
  "IncomeCards.titlePending": "Undisbursed",
  "IncomeCards.tooltipPending": "The amount of income that has not been disbursed to your account",
  "IncomeCards.titlePotentialEarnings": "Potential Earnings",
  "IncomeCards.tooltipPotentialEarnings": "Estimated income you can receive later if all transactions are completed",
  "IncomeCards.titleTotalClaims": "Total Claims",
  "IncomeCards.tooltipTotalClaims": "Your total income that is currently being processed for claims",
  "IncomeCards.titleTotalEarnings": "Total Overall Income",
  "IncomeCards.infoTooltipTotalEarnings": "Total Overall Income is the accumulation of all your income sources, including disbursed, undisbursed, potential earnings, and total claims.",
  "SuspendedAccountAlert.messageSuspended": "Your account is suspended, contact customer support for reactivation",
  "SuspendedAccountAlert.linkHere": "here",
  "RealtimeDashboardPage.titlePage": "Real-time Dashboard",
  "RealtimeDashboardPage.messageErrorLoad": "Failed to load dashboard data. Please try again later.",
  "RealtimeDashboardPage.titleOrders": "Orders",
  "RealtimeDashboardPage.subtitleOrders": "Order and delivery status information you need to monitor",
  "RealtimeDashboardPage.titleIncome": "Income",
  "RealtimeDashboardPage.subtitleIncome": "Information on potential income and disbursement status you receive",
  "RealtimeDashboardPage.titleNeedsAttention": "Needs Attention",
  "RealtimeDashboardPage.subtitleNeedsAttention": "Activities you need to pay attention to in order to maintain Shipper satisfaction",
  "RealtimeDashboardPage.titlePerformance": "Your Performance",
  "RealtimeDashboardPage.subtitlePerformance": "Activities you need to pay attention to in order to maintain Shipper satisfaction, monitor and continuously improve the quality of your deliveries",
  "RealtimeDashboardPage.ordersLabelWaitingConfirmation": "Waiting for Confirmation",
  "RealtimeDashboardPage.ordersTooltipWaitingConfirmation": "Your fleet has been registered for this order, please wait a maximum of 1 hour for confirmation from the Shipper.",
  "RealtimeDashboardPage.ordersLabelConfirmed": "Confirmed Orders",
  "RealtimeDashboardPage.ordersTooltipConfirmed": "List of confirmed orders that are in the fleet preparation stage for transport.",
  "RealtimeDashboardPage.ordersLabelScheduled": "Fleet Scheduled",
  "RealtimeDashboardPage.ordersTooltipScheduled": "List of orders with a set departure schedule, awaiting the loading process.",
  "RealtimeDashboardPage.ordersLabelLoading": "Loading Process",
  "RealtimeDashboardPage.ordersTooltipLoading": "List of orders currently in the process of being loaded onto the fleet at the loading location.",
  "RealtimeDashboardPage.ordersLabelUnloading": "Unloading Process",
  "RealtimeDashboardPage.ordersTooltipUnloading": "List of orders currently in the process of being unloaded from the fleet at the unloading location.",
  "RealtimeDashboardPage.ordersLabelDocumentPreparation": "Document Preparation",
  "RealtimeDashboardPage.ordersTooltipDocumentPreparation": "List of orders currently in the process of preparing and verifying shipping documents.",
  "RealtimeDashboardPage.ordersLabelDocumentDelivery": "Document Delivery Process",
  "RealtimeDashboardPage.ordersTooltipDocumentDelivery": "List of orders with documents currently being sent to the Shipper.",
  "RealtimeDashboardPage.ordersLabelCompleted": "Order Completed",
  "RealtimeDashboardPage.ordersTooltipCompleted": "List of transport service orders that have been completely processed, including document delivery and payment.",
  "RealtimeDashboardPage.alertsLabelNeedResponse": "Needs Response to Changes",
  "RealtimeDashboardPage.alertsTooltipNeedResponse": "Number of orders requiring a response to changes from the Shipper today",
  "RealtimeDashboardPage.alertsLabelNeedConfirmation": "Needs Ready Confirmation",
  "RealtimeDashboardPage.alertsTooltipNeedConfirmation": "Number of orders that require ready confirmation today",
  "RealtimeDashboardPage.alertsLabelNeedAssignment": "Needs Fleet Assignment",
  "RealtimeDashboardPage.alertsTooltipNeedAssignment": "Number of orders that do not have a fleet assigned today",
  "RealtimeDashboardPage.alertsLabelNewReviews": "New Reviews",
  "RealtimeDashboardPage.alertsTooltipNewReviews": "New reviews given by the Shipper for deliveries completed today",
  "RealtimeDashboardPage.alertsLabelSosReports": "SOS Reports",
  "RealtimeDashboardPage.alertsTooltipSosReports": "Number of SOS reports that require resolution today",
  "RealtimeDashboardPage.performanceLabelOverallRating": "Overall Driver Rating",
  "RealtimeDashboardPage.performanceTooltipOverallRating": "Rating is the average score from all assessments given by users to drivers who have completed their trips",
  "RealtimeDashboardPage.performanceLabelCancelledOrders": "Cancelled Orders",
  "RealtimeDashboardPage.performanceTooltipCancelledOrders": "Number of Cancelled Transport Service Orders, See Details for More Information on Cancellations",
  "RealtimeDashboardPage.performanceLabelPenalties": "Number of Penalties",
  "RealtimeDashboardPage.performanceTooltipPenalties": "Number of penalty points you received from order cancellations",
  "RealtimeDashboardPage.performanceUnitOrders": " Orders",
  "RealtimeDashboardPage.performanceUnitPenalties": " Penalties",
  "PotentialEarningsPage.breadcrumbDashboard": "Real-time Dashboard",
  "PotentialEarningsPage.titlePotentialEarnings": "Potential Earnings",
  "PotentialEarningsTable.messageErrorFetch": "Failed to fetch data. Please try again.",
  "PotentialEarningsTable.statusWaitingConfirmation": "Waiting for Confirmation",
  "PotentialEarningsTable.tooltipWaitingConfirmation": "Your fleet has been registered for this order, please wait a maximum of 1 hour for confirmation from the Shipper.",
  "PotentialEarningsTable.statusConfirmed": "Order Confirmed",
  "PotentialEarningsTable.statusScheduled": "Fleet Scheduled",
  "PotentialEarningsTable.statusLoading": "Loading Process",
  "PotentialEarningsTable.statusUnloading": "Unloading Process",
  "PotentialEarningsTable.statusDocumentPreparation": "Document Preparation",
  "PotentialEarningsTable.statusDocumentDelivery": "Document Delivery Process",
  "PotentialEarningsTable.statusNeedAssignment": "Needs Fleet Assignment",
  "PotentialEarningsTable.statusNeedResponse": "Needs Response to Change",
  "PotentialEarningsTable.statusNeedConfirmation": "Needs Ready Confirmation",
  "PotentialEarningsTable.columnOrderNumber": "Order No.",
  "PotentialEarningsTable.columnPotentialAmount": "Potential Earnings",
  "PotentialEarningsTable.columnStatus": "Order Status",
  "PotentialEarningsTable.buttonDetail": "Detail",
  "PotentialEarningsTable.filterLabelStatus": "Status",
  "PotentialEarningsTable.filterOptionWaitingConfirmation": "Waiting for Shipper Confirmation",
  "PotentialEarningsTable.filterOptionConfirmed": "Order Confirmed",
  "PotentialEarningsTable.filterOptionScheduled": "Fleet Scheduled",
  "PotentialEarningsTable.filterOptionNeedResponse": "Needs Response to Change",
  "PotentialEarningsTable.filterOptionNeedConfirmation": "Needs Ready Confirmation",
  "PotentialEarningsTable.filterOptionNeedAssignment": "Needs Fleet Assignment",
  "PotentialEarningsTable.filterOptionLoading": "Loading Process",
  "PotentialEarningsTable.filterOptionUnloading": "Unloading Process",
  "PotentialEarningsTable.filterOptionDocumentDelivery": "Document Delivery Process",
  "PotentialEarningsTable.searchPlaceholder": "Search Order",
  "PotentialEarningsTable.emptyStateTitle": "Oops, potential earnings are still empty",
  "PotentialEarningsTable.emptyStateSubtitle": "Start accepting requests now to display potential earnings data here",
  "PotentialEarningsTable.emptyStateButton": "View Requests",
  "PotentialEarningsTable.headerTotalPotential": "Total Potential Earnings",
  "DashboardDataTable.searchPlaceholderDefault": "Search...",
  "DashboardDataTable.notFoundSearchTitle": "Keyword Not Found",
  "DashboardDataTable.notFoundFilterPart1": "Data Not Found.",
  "DashboardDataTable.notFoundFilterPart2": "Please try removing some filters",
  "DashboardDataTable.emptyDataTitle": "No data",
  "UlasanPage.breadcrumbDashboard": "Real-time Dashboard",
  "UlasanPage.titleReviewList": "Review List",
  "UlasanTable.toastErrorMarkAsRead": "Failed to mark review as read",
  "UlasanTable.toastSuccessMarkAsRead": "Review successfully marked as read",
  "UlasanTable.columnDate": "Date",
  "UlasanTable.columnOrderNumber": "Order No.",
  "UlasanTable.columnDriver": "Driver",
  "UlasanTable.columnRatingAndReview": "Rating and Review",
  "UlasanTable.filterLabelRating": "Rating",
  "UlasanTable.filterOption5Stars": "5 Stars",
  "UlasanTable.filterOption4Stars": "4 Stars",
  "UlasanTable.filterOption3Stars": "3 Stars",
  "UlasanTable.filterOption2Stars": "2 Stars",
  "UlasanTable.filterOption1Star": "1 Star",
  "UlasanTable.periodOptionAll": "All Periods (Default)",
  "UlasanTable.periodOptionToday": "Today",
  "UlasanTable.periodOptionLast7Days": "Last 7 Days",
  "UlasanTable.periodOptionLast30Days": "Last 30 Days",
  "UlasanTable.periodOptionLastYear": "Last 1 Year",
  "UlasanTable.tabNew": "New",
  "UlasanTable.tabRead": "Read",
  "UlasanTable.buttonDownload": "Download",
  "UlasanTable.searchPlaceholder": "Search Reviews",
  "UlasanTable.emptyStateTitle": "Oops, Review List is empty",
  "UlasanTable.emptyStateSubtitle": "Reviews from shippers will be displayed here",
  "UlasanTable.emptyStateButton": "View Requests",
  "UlasanTable.buttonMarkAsRead": "Mark as Read",
  "UlasanTable.buttonCancel": "Cancel",
  "UlasanTable.tooltipSelectReview": "Select at least 1 review to mark as read",
  "UlasanTable.headerTotalRating": "Total Rating",
  "UlasanTable.modalConfirmDescription": "The review will be moved to the Read tab and will no longer appear in the Review List. Are you sure you want to continue?",
  "UlasanTable.modalConfirmYes": "Yes",
  "UlasanTable.modalConfirmNo": "No",
  "RatingDriverPage.breadcrumbDashboard": "Real-time Dashboard",
  "RatingDriverPage.titleOverallDriverRating": "Overall Driver Rating",
  "DriverRatingTable.messageErrorFetch": "Failed to fetch data. Please try again.",
  "DriverRatingTable.columnNo": "No.",
  "DriverRatingTable.columnDriver": "Driver",
  "DriverRatingTable.columnRating": "Rating",
  "DriverRatingTable.columnOrderCount": "Number of Orders",
  "DriverRatingTable.unitOrders": "{count} Orders",
  "DriverRatingTable.buttonHistory": "History",
  "DriverRatingTable.filterLabelRating": "Rating",
  "DriverRatingTable.filterOption5Stars": "5 Stars",
  "DriverRatingTable.filterOption4Stars": "4 Stars",
  "DriverRatingTable.filterOption3Stars": "3 Stars",
  "DriverRatingTable.filterOption2Stars": "2 Stars",
  "DriverRatingTable.filterOption1Star": "1 Star",
  "DriverRatingTable.buttonDownload": "Download",
  "DriverRatingTable.searchPlaceholder": "Search Driver Name / WhatsApp No.",
  "DriverRatingTable.emptyStateTitle": "Oops, driver ratings are still empty",
  "DriverRatingTable.emptyStateSubtitle": "Start accepting requests now to display driver rating data here",
  "DriverRatingTable.emptyStateButton": "View Requests",
  "DriverRatingTable.headerOverallRating": "Overall Driver Rating",
  "RatingDriverHistoryPage.breadcrumbDashboard": "Real-time Dashboard",
  "RatingDriverHistoryPage.breadcrumbOverallRating": "Overall Driver Rating",
  "RatingDriverHistoryPage.titlePage": "Overall Driver Rating History",
  "RatingHistoryTable.messageErrorFetch": "Failed to load rating history.",
  "RatingHistoryTable.columnDate": "Date",
  "RatingHistoryTable.columnOrderNumber": "Order No.",
  "RatingHistoryTable.columnDriverName": "Driver Name",
  "RatingHistoryTable.columnFleet": "Fleet",
  "RatingHistoryTable.labelCarrier": "Carrier :",
  "RatingHistoryTable.columnRatingReview": "Rating and Review",
  "RatingHistoryTable.filterLabelRating": "Rating",
  "RatingHistoryTable.filterOption5Stars": "5 Stars",
  "RatingHistoryTable.filterOption4Stars": "4 Stars",
  "RatingHistoryTable.filterOption3Stars": "3 Stars",
  "RatingHistoryTable.filterOption2Stars": "2 Stars",
  "RatingHistoryTable.filterOption1Star": "1 Star",
  "RatingHistoryTable.periodOptionAll": "All Periods (Default)",
  "RatingHistoryTable.periodOptionToday": "Today",
  "RatingHistoryTable.periodOptionLast7Days": "Last 7 Days",
  "RatingHistoryTable.periodOptionLast30Days": "Last 30 Days",
  "RatingHistoryTable.periodOptionLastYear": "Last 1 Year",
  "RatingHistoryTable.buttonDownload": "Download",
  "RatingHistoryTable.searchPlaceholder": "Search Order No. / Fleet",
  "RatingHistoryTable.headerTotalRating": "Total Rating",
  "PenaltyPage.breadcrumbDashboard": "Real-time Dashboard",
  "PenaltyPage.titlePage": "Number of Penalties",
  "PenaltyTable.messageErrorFetch": "Failed to load penalty data.",
  "PenaltyTable.columnCancellationDate": "Cancellation Date",
  "PenaltyTable.columnOrderNumber": "Order No.",
  "PenaltyTable.columnFleet": "Fleet",
  "PenaltyTable.labelCarrier": "Carrier :",
  "PenaltyTable.columnReason": "Reason",
  "PenaltyTable.periodOptionAll": "All Periods (Default)",
  "PenaltyTable.periodOptionToday": "Today",
  "PenaltyTable.periodOptionLast7Days": "Last 7 Days",
  "PenaltyTable.periodOptionLast30Days": "Last 30 Days",
  "PenaltyTable.periodOptionLastYear": "Last 1 Year",
  "PenaltyTable.buttonDownload": "Download",
  "PenaltyTable.searchPlaceholder": "Search Order No. / Police No. / Fleet",
  "PenaltyTable.emptyStateTitle": "No cancelled orders",
  "PenaltyTable.emptyStateSubtitle": "Penalties are calculated from the number of order cancellations by the Transporter or Shipper",
  "PenaltyTable.headerTotalPenalty": "Total Penalties :",
  "PenaltyTable.unitPenalty": "{count} Penalties",
  "Period.actionSelectPeriod": "Select Period",
  "Period.labelRecentlySearched": "Recently Searched",
  "Period.placeholderStartDate": "Start Period",
  "Period.labelUntil": "to",
  "Period.placeholderEndDate": "End Period",
  "Period.messageErrorStartDateRequired": "Start period is required",
  "Period.messageErrorEndDateRequired": "End period is required",
  "Period.messageErrorEndDateBeforeStart": "End period cannot be earlier than start period",
  "Period.messageErrorRangeTooLarge": "Maximum range is 1 year from the start period",
  "Period.buttonApply": "Apply",
  "csDashboard.pageTitle": "Real-time Dashboard",
  "csDashboard.ordersSectionTitle": "Orders",
  "csDashboard.ordersSectionSubtitle": "Order and shipment status information from all Muatrans Transporters",
  "csDashboard.attentionSectionTitle": "Needs Attention",
  "csDashboard.attentionSectionSubtitle": "Transporter activities you need to pay attention to for Shipper satisfaction",
  "csDashboard.orderStatus.waitingConfirmation": "Waiting for Confirmation",
  "csDashboard.orderStatus.confirmed": "Order Confirmed",
  "csDashboard.orderStatus.scheduled": "Fleet Scheduled",
  "csDashboard.orderStatus.loading": "Loading Process",
  "csDashboard.orderStatus.unloading": "Unloading Process",
  "csDashboard.orderStatus.docPrep": "Document Preparation",
  "csDashboard.orderStatus.docDelivery": "Document Delivery Process",
  "csDashboard.orderStatus.completed": "Order Completed",
  "csDashboard.attention.needsChangeResponse": "Needs Change Response",
  "csDashboard.attention.needsReadyConfirmation": "Needs Ready Confirmation",
  "csDashboard.attention.needsFleetAssignment": "Needs Fleet Assignment",
  "csDashboard.attention.newReviews": "Review List",
  "csDashboard.attention.sosReports": "SOS Reports",
  "csDashboard.ratingCardTitle": "Overall Transporter Rating",
  "csDashboard.ratingCardLink": "View Details",
  "csDashboard.tooltip.waitingConfirmation": "List of instant orders awaiting payment by the shipper.",
  "csDashboard.tooltip.confirmed": "List of confirmed orders that are in the fleet preparation stage for transport.",
  "csDashboard.tooltip.scheduled": "List of orders with a set departure schedule, awaiting the loading process.",
  "csDashboard.tooltip.loading": "List of orders currently in the process of loading goods into the fleet at the loading location.",
  "csDashboard.tooltip.unloading": "List of orders currently in the process of unloading goods from the fleet at the unloading location.",
  "csDashboard.tooltip.docPrep": "List of orders in the process of preparing and verifying shipping documents.",
  "csDashboard.tooltip.docDelivery": "List of orders with documents currently in the process of being sent to the Shipper.",
  "csDashboard.tooltip.completed": "List of transport service orders that have been completely processed, including document delivery and payment.",
  "csDashboard.tooltip.needsChangeResponse": "Number of orders requiring change confirmation from the shipper today.",
  "csDashboard.tooltip.needsReadyConfirmation": "Number of orders that need ready confirmation today.",
  "csDashboard.tooltip.needsFleetAssignment": "Number of orders that do not have a fleet assigned today.",
  "csDashboard.tooltip.newReviews": "New reviews given by shippers for deliveries completed today.",
  "csDashboard.tooltip.sosReports": "Number of SOS reports that require resolution action today.",
  "csRatingTransporter.pageTitle": "Overall Transporter Rating",
  "csRatingTransporter.searchPlaceholder": "Search Transporter Name",
  "csRatingTransporter.filter.rating": "Rating",
  "csRatingTransporter.table.header.no": "No.",
  "csRatingTransporter.table.header.transporter": "Transporter",
  "csRatingTransporter.table.header.rating": "Rating",
  "csRatingTransporter.table.header.orderCount": "Total Orders",
  "csRatingTransporter.table.button.detail": "Details",
  "csRatingTransporter.button.download": "Download",
  "csRatingTransporter.emptyState.title": "Oops, overall transporter rating is still empty",
  "csRatingTransporter.emptyState.subtitle": "No Shipper has rated a Transporter yet",
  "csRatingTransporter.summaryTitle": "Overall Transporter Rating",
  "csRatingTransporter.filter.rating.fiveStars": "5 Stars",
  "csRatingTransporter.filter.rating.fourStars": "4 Stars",
  "csRatingTransporter.filter.rating.threeStars": "3 Stars",
  "csRatingTransporter.filter.rating.twoStars": "2 Stars",
  "csRatingTransporter.filter.rating.oneStar": "1 Star",
  "csDriverRating.pageTitle": "Transporter Driver Rating Details",
  "csDriverRating.button.download": "Download",
  "csDriverRating.transporterLabel": "Transporter",
  "csDriverRating.searchPlaceholder": "Search Driver Name",
  "csDriverRating.filter.rating": "Rating",
  "csDriverRating.table.header.no": "No.",
  "csDriverRating.table.header.driver": "Driver",
  "csDriverRating.table.header.rating": "Rating",
  "csDriverRating.table.header.orderCount": "Total Orders",
  "csDriverRating.summaryTitle": "Overall Driver Rating",
  "csDriverRating.emptyState.title": "Oops, driver rating is still empty",
  "csDriverRating.emptyState.subtitle": "No Shipper has rated a Driver from this Transporter yet",
  "csDriverRating.table.orderUnit": "Orders"
}
